<?xml version="1.0" encoding="utf-8"?>
<Actions xsi:noNamespaceSchemaLocation="../../../ConsoleLauncher/bin/Debug/netcoreapp3.0/TxWebTests.xsd" xmlns:xsi="http://www.w3.org/2001/XMLSchema-instance">
  <TestHeader>
    <Parameters>
      <testData>
        <testPriority>0</testPriority>
        <testDescription>Check the Language of the calender in "Date" and "Date and Time" attribute , And of the attributes in tab "Inherited" for 'Chinese' language</testDescription>
      </testData>
      <teexmaData>
        <customerResPath>customerResPath</customerResPath>
        <teexmaVersion>teexmaVersion</teexmaVersion>
        <databasePath>databasePath</databasePath>
      </teexmaData>
    </Parameters>
  </TestHeader>
  <TxInterface>
    <Actions>
      <Login>
        <Parameters>
          <login>Administrator</login>
          <password>aaaaa</password>
          <langage>Chinese</langage>
        </Parameters>
      </Login>
      <MainWindow>
        <Actions>
          <NavigationTree>
            <Actions>
              <SelectOT>
                <Actions>
                  <Select>
                    <Parameters>
                      <value>TEST_WriteView</value>
                    </Parameters>
                  </Select>
                </Actions>
              </SelectOT>
              <EntityTree>
                <Actions>
                  <SelectEntity>
                    <Parameters><nodes><path>New</path></nodes></Parameters>
                  </SelectEntity>
                </Actions>
              </EntityTree>
            </Actions>
          </NavigationTree>
          <Edit>
            <Actions>
              <Content>
                <Actions>
                	<Date>
                		<Parameters>
                			<attrId>95</attrId>
                		</Parameters>
                		<Actions>
                			<ReadMonthNames>
                				<Actions>
                					<ElementAt>
                						<Parameters>
                							<index>0</index>
                						</Parameters>
                						<ExpectedResult>一月</ExpectedResult>
                					</ElementAt>
                					<ElementAt>
                						<Parameters>
                							<index>1</index>
                						</Parameters>
                						<ExpectedResult>二月</ExpectedResult>
                					</ElementAt>
                					<ElementAt>
                						<Parameters>
                							<index>2</index>
                						</Parameters>
                						<ExpectedResult>三月</ExpectedResult>
                					</ElementAt>
                					<ElementAt>
                						<Parameters>
                							<index>3</index>
                						</Parameters>
                						<ExpectedResult>四月</ExpectedResult>
                					</ElementAt>
                					<ElementAt>
                						<Parameters>
                							<index>4</index>
                						</Parameters>
                						<ExpectedResult>五月</ExpectedResult>
                					</ElementAt>
                					<ElementAt>
                						<Parameters>
                							<index>5</index>
                						</Parameters>
                						<ExpectedResult>六月</ExpectedResult>
                					</ElementAt>
                					<ElementAt>
                						<Parameters>
                							<index>6</index>
                						</Parameters>
                						<ExpectedResult>七月</ExpectedResult>
                					</ElementAt>
                					<ElementAt>
                						<Parameters>
                							<index>7</index>
                						</Parameters>
                						<ExpectedResult>八月</ExpectedResult>
                					</ElementAt>
                					<ElementAt>
                						<Parameters>
                							<index>8</index>
                						</Parameters>
                						<ExpectedResult>九月</ExpectedResult>
                					</ElementAt>
                					<ElementAt>
                						<Parameters>
                							<index>9</index>
                						</Parameters>
                						<ExpectedResult>十月</ExpectedResult>
                					</ElementAt>
                					<ElementAt>
                						<Parameters>
                							<index>10</index>
                						</Parameters>
                						<ExpectedResult>十一月</ExpectedResult>
                					</ElementAt>
                					<ElementAt>
                						<Parameters>
                							<index>11</index>
                						</Parameters>
                						<ExpectedResult>十二月</ExpectedResult>
                					</ElementAt>
                					</Actions>
                			</ReadMonthNames>
                			<IsWeekDaysTranslated>
                				<Parameters>
                					<cultureName>zh-CHS</cultureName></Parameters>
                			</IsWeekDaysTranslated></Actions>
                	</Date>
                </Actions>
              </Content>
            </Actions>
          </Edit>
        </Actions>
      </MainWindow>
    </Actions>
  </TxInterface>
</Actions>