<?xml version="1.0" encoding="utf-8"?>
<Actions xsi:noNamespaceSchemaLocation="../../../ConsoleLauncher/bin/Debug/netcoreapp3.0/TxWebTests.xsd"
	xmlns:xsi="http://www.w3.org/2001/XMLSchema-instance">
	<TestHeader>
		<Parameters>
			<testData>
				<testPriority>0</testPriority>
				<testDescription>Rights on an object truned to read on the connected user.</testDescription>
			</testData>
			<teexmaData>
				<customerResPath>customerResPath</customerResPath>
				<teexmaVersion>teexmaVersion</teexmaVersion>
				<databasePath>databasePath</databasePath>
			</teexmaData>
		</Parameters>
	</TestHeader>
	<TxInterface>
		<Actions>
			<Login>
				<Parameters>
					<login>Sarah&#160;Morra</login>
					<password>aaaaa</password>
				</Parameters>
			</Login>
			<MainWindow>
				<Actions>
					<NavigationTree>
						<Actions>
							<IsOTPresent>
								<Parameters>
									<value>Company</value>
								</Parameters>
							</IsOTPresent></Actions>
					</NavigationTree>
					<NavigationTree>
						<Actions>
							<SelectOT>
								<Actions>
									<Select>
										<Parameters>
											<value>Company</value>
										</Parameters>
									</Select></Actions>
							</SelectOT>
							<EntityTree>
								<Actions>
									<EntitytPresence>
										<Parameters>
											<nodes>
												<path>Company 1</path></nodes>
											<presence>true</presence>
										</Parameters>
									</EntitytPresence>
									<SelectEntity>
										<Parameters>
											<nodes>
												<path>Company 1</path></nodes>
										</Parameters>
									</SelectEntity></Actions>
							</EntityTree></Actions>
					</NavigationTree>
					<ReadForm>
						<Actions>
							<AttributeIsDiplayed>
								<Parameters>
									<attrId>78</attrId>
								</Parameters>
								<ExpectedResult>true</ExpectedResult>
							</AttributeIsDiplayed>
							<Read>
								<DTText>
									<Parameters>
										<attrId>78</attrId>
									</Parameters>
									<ExpectedResult>
										<value>Company 1</value>
									</ExpectedResult>
								</DTText>
								
							</Read>
							<AttributeName>
								<Parameters>
									<attrId>92</attrId>
								</Parameters>
								<ExpectedResult>Agency</ExpectedResult>
							</AttributeName>
							<AttributeIsDiplayed>
								<Parameters>
									<attrId>82</attrId>
								</Parameters>
								<ExpectedResult>true</ExpectedResult>
							</AttributeIsDiplayed>
							<Read>
								<DTText>
									<Parameters>
										<attrId>82</attrId>
									</Parameters>
									<ExpectedResult>
										<value>Description</value>
									</ExpectedResult>
								</DTText>
								
							</Read></Actions>
					</ReadForm>
					<LaunchModel>
						<Parameters>
							<modelName>Add read rights to connected user</modelName>
						</Parameters>
					</LaunchModel><NavigationTree>
						<Actions>
							<SelectOT>
								<Actions>
									<Select>
										<Parameters>
											<value>Agencies&#160;of&#160;company&#160;-&#160;Business&#160;view</value>
										</Parameters>
									</Select></Actions>
							</SelectOT></Actions>
					</NavigationTree>
					<NavigationTree>
						<Actions>
							<SelectOT>
								<Actions>
									<Select>
										<Parameters>
											<value>Company</value>
										</Parameters>
									</Select></Actions>
							</SelectOT>
							<EntityTree>
								<Actions>
									<SelectEntity>
										<Parameters>
											<nodes>
												<path>Company 1</path></nodes>
										</Parameters>
									</SelectEntity></Actions>
							</EntityTree></Actions>
					</NavigationTree><ReadForm>
						<Actions>
							<AttributeIsDiplayed>
								<Parameters>
									<attrId>78</attrId>
								</Parameters>
								<ExpectedResult>true</ExpectedResult>
							</AttributeIsDiplayed>
							<Read>
								<DTText>
									<Parameters>
										<attrId>78</attrId>
									</Parameters>
									<ExpectedResult>
										<value>Company 1</value>
									</ExpectedResult>
								</DTText>
								
							</Read>
							<AttributeName>
								<Parameters>
									<attrId>92</attrId>
								</Parameters>
								<ExpectedResult>Agency</ExpectedResult>
							</AttributeName><AttributeIsDiplayed>
								<Parameters>
									<attrId>82</attrId>
								</Parameters>
								<ExpectedResult>true</ExpectedResult>
							</AttributeIsDiplayed>
							<Read>
								<DTText>
									<Parameters>
										<attrId>82</attrId>
									</Parameters>
									<ExpectedResult>
										<value>Description</value>
									</ExpectedResult>
								</DTText>
								
							</Read></Actions>
					</ReadForm>
					<IsEditButtonEnable>
						<ExpectedResult>false</ExpectedResult></IsEditButtonEnable>
				</Actions>
			</MainWindow>
		</Actions>
	</TxInterface>
</Actions>