<?xml version="1.0" encoding="utf-8"?>
<Actions xsi:noNamespaceSchemaLocation="../../../ConsoleLauncher/bin/Debug/netcoreapp3.0/TxWebTests.xsd" xmlns:xsi="http://www.w3.org/2001/XMLSchema-instance">
  <TestHeader>
    <Parameters>
      <testData>
        <testPriority>0</testPriority>
        <testDescription>Go to TEEXMA WEB, select OT 'ModelApplications'. Turn to WriteForm and try to add a new Object,When the Object has been correctly added, the value of its Attribute 'TEST_Launch_When an Object is created' will be automatically filled with 66</testDescription>
      </testData>
      <teexmaData>
        <customerResPath>customerResPath</customerResPath>
        <teexmaVersion>teexmaVersion</teexmaVersion>
        <databasePath>databasePath</databasePath>
      </teexmaData>
    </Parameters>
  </TestHeader>
  <TxInterface>
    <Message>Associativeteststart</Message>
    <Actions>
      <Login>
        <Parameters>
          <login>Administrator</login>
          <password>aaaaa</password>
        </Parameters>
      </Login>
      <MainWindow>
        <Actions>
          <NavigationTree>
            <Actions>
              <EntityTree>
                <Actions>
                  <SelectEntity>
                    <Parameters><nodes><path>Home</path></nodes></Parameters>
                  </SelectEntity>
                </Actions>
              </EntityTree>
            </Actions>
          </NavigationTree>
        </Actions>
      </MainWindow>
    </Actions>
  </TxInterface>
</Actions>