<?xml version="1.0" encoding="UTF-8"?>
<Actions xmlns:xsi="http://www.w3.org/2001/XMLSchema-instance" xsi:noNamespaceSchemaLocation="../../../ConsoleLauncher/bin/Debug/netcoreapp3.0/TxWebTests.xsd">
  <TestHeader>
    <Parameters>
      <testData>
        <testPriority>0</testPriority>
        <testDescription>Check the display mode of  a choice guide with "Advanced Question " which has "Modiafiable By Question" unticked for OT but ticked for an attribute (Date type)</testDescription>
      </testData>
      <teexmaData>
        <customerResPath>customerResPath</customerResPath>
        <teexmaVersion>teexmaVersion</teexmaVersion>
        <databasePath>databasePath</databasePath>
      </teexmaData>
    </Parameters>
  </TestHeader>
  <TxInterface>
    <Actions>
      <Login>
        <Parameters>
          <login>Administrator</login>
          <password>aaaaa</password>
        </Parameters>
      </Login>
      <MainWindow>
        <Actions>
          <IfPopUpPresent></IfPopUpPresent><ChoiceGuide>
            <Actions>
              <Content>
                <Actions>
                  <ChoiceGuideFromTemplate>
                    <Parameters>
                      <template>AdvancedQuestion</template>
                    </Parameters>
                    <Actions>
                      <Content>
                        <Actions>
                          <Formulaire>
                          	<Actions>
                          		<DateCriteria>
                          			<Parameters>
                          				<id>47</id>
                          			</Parameters>
                          			<Actions>
                          				<GreaterThan></GreaterThan>
                          				<LowerValue>
                          					<Parameters>
                          						<value>10/05/18</value>
                          					</Parameters>
                          				</LowerValue>
                          				<GreaterThan></GreaterThan>
                          				<GreaterThan></GreaterThan>
                          				<LowerDate>
                          					<Actions>
                          						<Year>
                          							<Parameters>
                          								<year>2019</year>
                          							</Parameters>
                          						</Year>
                          						<Month>
                          							<Parameters>
                          								<month>May</month>
                          							</Parameters>
                          						</Month>
                          						<Day>
                          							<Parameters>
                          								<day>8</day>
                          							</Parameters>
                          						</Day></Actions>
                          				</LowerDate>
                          				<StrictlyGreaterThan></StrictlyGreaterThan>
                          				<LowerTolerance></LowerTolerance>
                          				<LowerToleranceValue>
                          					<Actions>
                          						<Write>
                          							<Parameters>
                          								<value>2</value>
                          							</Parameters>
                          						</Write></Actions>
                          				</LowerToleranceValue>
                          				<LessThan></LessThan>
                          				<UpperValue>
                          					<Parameters>
                          						<value>10/05/18</value>
                          					</Parameters>
                          				</UpperValue>
                          				<UpperDate>
                          					<Actions><Year>
                          							<Parameters>
                          								<year>2019</year>
                          							</Parameters>
                          						</Year>
                          						<Month>
                          							<Parameters>
                          								<month>May</month>
                          							</Parameters>
                          						</Month>
                          						<Day>
                          							<Parameters>
                          								<day>8</day>
                          							</Parameters>
                          						</Day></Actions>
                          				</UpperDate>
                          				<StrictlyLessThan></StrictlyLessThan>
                          				<UpperTolerance></UpperTolerance>
                          				<UpperToleranceValue>
                          					<Actions>
                          						<Write>
                          							<Parameters>
                          								<value>2</value>
                          							</Parameters>
                          						</Write></Actions>
                          				</UpperToleranceValue>
                          				<EqualTo></EqualTo>
                          				<EqualToValue>
                          					<Parameters>
                          						<value>10/05/18</value>
                          					</Parameters>
                          				</EqualToValue>
                          				<EqualToDate>
                          					<Actions><Year>
                          							<Parameters>
                          								<year>2019</year>
                          							</Parameters>
                          						</Year>
                          						<Month>
                          							<Parameters>
                          								<month>May</month>
                          							</Parameters>
                          						</Month>
                          						<Day>
                          							<Parameters>
                          								<day>8</day>
                          							</Parameters>
                          						</Day></Actions>
                          				</EqualToDate>
                          				<EqualTolerance></EqualTolerance>
                          				<EqualToleranceValue>
                          					<Actions>
                          						<Write>
                          							<Parameters>
                          								<value>2</value>
                          							</Parameters>
                          						</Write></Actions>
                          				</EqualToleranceValue>
                          				<Range></Range>
                          				<LowerValue>
                          					<Parameters>
                          						<value>10/05/18</value>
                          					</Parameters>
                          				</LowerValue>
                          				<LowerDate>
                          					<Actions>
                          						<Year>
                          							<Parameters>
                          								<year>2019</year>
                          							</Parameters>
                          						</Year>
                          						<Month>
                          							<Parameters>
                          								<month>May</month>
                          							</Parameters>
                          						</Month>
                          						<Day>
                          							<Parameters>
                          								<day>8</day>
                          							</Parameters>
                          						</Day></Actions>
                          				</LowerDate>
                          				<StrictlyGreaterThan></StrictlyGreaterThan>
                          				<LowerTolerance></LowerTolerance>
                          				<LowerTolerance></LowerTolerance>
                          				<LowerToleranceValue>
                          					<Actions>
                          						<Write>
                          							<Parameters>
                          								<value>2</value>
                          							</Parameters>
                          						</Write></Actions>
                          				</LowerToleranceValue>
                          				<UpperValue>
                          					<Parameters>
                          						<value>10/05/18</value>
                          					</Parameters>
                          				</UpperValue>
                          				<UpperDate>
                          					<Actions><Year>
                          							<Parameters>
                          								<year>2019</year>
                          							</Parameters>
                          						</Year>
                          						<Month>
                          							<Parameters>
                          								<month>May</month>
                          							</Parameters>
                          						</Month>
                          						<Day>
                          							<Parameters>
                          								<day>8</day>
                          							</Parameters>
                          						</Day></Actions>
                          				</UpperDate>
                          				<StrictlyLessThan></StrictlyLessThan>
                          				<UpperTolerance></UpperTolerance>
                          				<UpperTolerance></UpperTolerance>
                          				<UpperToleranceValue>
                          					<Actions>
                          						<Write>
                          							<Parameters>
                          								<value>2</value>
                          							</Parameters>
                          						</Write></Actions>
                          				</UpperToleranceValue>
                          			</Actions>
                          		</DateCriteria></Actions>
                          </Formulaire>
                        </Actions>
                      </Content>
                    </Actions>
                  </ChoiceGuideFromTemplate>
                </Actions>
              </Content>
            </Actions>
          </ChoiceGuide>
        </Actions>
      </MainWindow>
    </Actions>
  </TxInterface>
</Actions>